setup.py
simple_distribution/Binomialdistribution.py
simple_distribution/Gaussiandistribution.py
simple_distribution/Generaldistribution.py
simple_distribution/__init__.py
simple_distribution.egg-info/PKG-INFO
simple_distribution.egg-info/SOURCES.txt
simple_distribution.egg-info/dependency_links.txt
simple_distribution.egg-info/not-zip-safe
simple_distribution.egg-info/top_level.txt