Metadata-Version: 1.0
Name: simple-distribution
Version: 0.1
Summary: Gaussian and Binomial distributions
Home-page: UNKNOWN
Author: forhad
Author-email: fhossain1@isrt.ac.bd
License: UNKNOWN
Platform: UNKNOWN
